dhl_poland_lib/__init__.py
dhl_poland_lib/services.py
carrier.dhl_poland-2021.11.dist-info/WHEEL
carrier.dhl_poland-2021.11.dist-info/METADATA
carrier.dhl_poland-2021.11.dist-info/RECORD
