Metadata-Version: 2.1
Name: carrier.dhl-poland
Version: 2021.11
Summary: DHL Parcel Poland Web API Schemas Python Data Types library
Home-page: https://github.com/purplship/purplship-carriers/tree/main/schemas/carrier.dhl_poland
License: Apache-2.0
Author: Purplship
Author-email: hello@purplship.com
Requires-Python: >=3.6,<4.0
Classifier: Intended Audience :: Developers
Classifier: License :: OSI Approved :: Apache Software License
Classifier: Operating System :: OS Independent
Classifier: Programming Language :: Python :: 3
Classifier: Programming Language :: Python :: 3.10
Classifier: Programming Language :: Python :: 3.6
Classifier: Programming Language :: Python :: 3.7
Classifier: Programming Language :: Python :: 3.8
Classifier: Programming Language :: Python :: 3.9
Requires-Dist: lxml
Requires-Dist: six
Project-URL: Repository, https://github.com/purplship/purplship-carriers
